icat/__init__.py
icat/__main__.py
ipython_icat-0.4.1.dist-info/licenses/LICENSE.md
ipython_icat-0.4.1.dist-info/METADATA
ipython_icat-0.4.1.dist-info/WHEEL
ipython_icat-0.4.1.dist-info/top_level.txt
ipython_icat-0.4.1.dist-info/RECORD
