Metadata-Version: 2.4
Name: ipython-icat
Version: 0.4.1
Summary: IPython magic command for displaying images in kitty terminal
Author-email: Tony Kabilan Okeke <tonykabilanokeke@gmail.com>
Project-URL: Homepage, https://github.com/Kabilan108/ipython-icat
Keywords: ipython,magic,image,display,kitty,icat,ipython extension,ghostty
Requires-Python: >=3.8
License-File: LICENSE.md
Requires-Dist: ipython
Requires-Dist: matplotlib
Requires-Dist: pillow
Dynamic: license-file
